tinylib/AVL_tree.py
tinylib/__init__.py
tinylib/alg.py
tinylib/bin_node.py
tinylib/bin_tree.py
tinylib/bst.py
tinylib/graph.py
tinylib/hash_table.py
tinylib/linked_list.py
tinylib/listADT.py
tinylib/priority_queue.py
tinylib/queues.py
tinylib/stack.py
tinylib/vector.py
tinylib/vectorADT.py
tinylib-0.1.8.dist-info/LICENSE.txt.txt
tinylib-0.1.8.dist-info/METADATA
tinylib-0.1.8.dist-info/WHEEL
tinylib-0.1.8.dist-info/top_level.txt
tinylib-0.1.8.dist-info/RECORD
